README
setup.py
src/django_restrictip.egg-info/PKG-INFO
src/django_restrictip.egg-info/SOURCES.txt
src/django_restrictip.egg-info/dependency_links.txt
src/django_restrictip.egg-info/requires.txt
src/django_restrictip.egg-info/top_level.txt
src/restrictip/__init__.py
src/restrictip/admin.py
src/restrictip/fields.py
src/restrictip/middleware.py
src/restrictip/models.py
src/restrictip/tests.py